podcast_archiver/__init__.py
podcast_archiver/base.py
podcast_archiver/cli.py
podcast_archiver/compat.py
podcast_archiver/config.py
podcast_archiver/console.py
podcast_archiver/constants.py
podcast_archiver/database.py
podcast_archiver/download.py
podcast_archiver/enums.py
podcast_archiver/exceptions.py
podcast_archiver/logging.py
podcast_archiver/models/__init__.py
podcast_archiver/models/episode.py
podcast_archiver/models/feed.py
podcast_archiver/models/field_types.py
podcast_archiver/models/misc.py
podcast_archiver/processor.py
podcast_archiver/session.py
podcast_archiver/types.py
podcast_archiver/urls/__init__.py
podcast_archiver/urls/base.py
podcast_archiver/urls/base64.py
podcast_archiver/urls/fireside.py
podcast_archiver/urls/prefixed.py
podcast_archiver/urls/soundcloud.py
podcast_archiver/urls/via_apple.py
podcast_archiver/utils/__init__.py
podcast_archiver/utils/pretty_printing.py
podcast_archiver/utils/progress.py
podcast_archiver-2.3.5.dist-info/LICENSE
podcast_archiver-2.3.5.dist-info/METADATA
podcast_archiver-2.3.5.dist-info/WHEEL
podcast_archiver-2.3.5.dist-info/entry_points.txt
podcast_archiver-2.3.5.dist-info/RECORD
