Metadata-Version: 2.3
Name: podcast-archiver
Version: 2.3.5
Summary: Archive all episodes from your favorite podcasts
License: MIT
Author: Jan Willhaus
Author-email: mail@janwillhaus.de
Requires-Python: >=3.10,<4.0
Classifier: Development Status :: 4 - Beta
Classifier: Environment :: Console
Classifier: Intended Audience :: Information Technology
Classifier: License :: OSI Approved :: MIT License
Classifier: Operating System :: MacOS
Classifier: Operating System :: Microsoft :: Windows
Classifier: Operating System :: POSIX :: Linux
Classifier: Programming Language :: Python :: 3
Classifier: Programming Language :: Python :: 3.10
Classifier: Programming Language :: Python :: 3.11
Classifier: Programming Language :: Python :: 3.12
Classifier: Programming Language :: Python :: 3.13
Classifier: Topic :: Multimedia
Classifier: Topic :: Multimedia :: Sound/Audio
Classifier: Topic :: System :: Archiving
Classifier: Topic :: Utilities
Requires-Dist: feedparser (>=6.0.10,<7.0.0)
Requires-Dist: platformdirs (>=3.4,<5.0)
Requires-Dist: pydantic (>=2.7.4,<3.0.0)
Requires-Dist: python-slugify (>=8.0.1,<9.0.0)
Requires-Dist: pyyaml (>=6.0,<7.0)
Requires-Dist: requests (>=2.29.0,<3.0.0)
Requires-Dist: rich-click (>=1.8.0,<2.0.0)
Requires-Dist: tqdm (>=4.66.4,<5.0.0)
Project-URL: Bug Reports, https://codeberg.org/janw/podcast-archiver/issues
Project-URL: Repository, https://codeberg.org/janw/podcast-archiver
